LICENSE
MANIFEST.in
README.rst
setup.cfg
setup.py
nie_sentry_auth_oidc.egg-info/PKG-INFO
nie_sentry_auth_oidc.egg-info/SOURCES.txt
nie_sentry_auth_oidc.egg-info/dependency_links.txt
nie_sentry_auth_oidc.egg-info/entry_points.txt
nie_sentry_auth_oidc.egg-info/not-zip-safe
nie_sentry_auth_oidc.egg-info/requires.txt
nie_sentry_auth_oidc.egg-info/top_level.txt
oidc/__init__.py
oidc/apps.py
oidc/constants.py
oidc/provider.py
oidc/views.py
oidc/templates/oidc/configure.html